pyEventHook/__init__.py
pyEventHook-0.0.1.dist-info/LICENSE
pyEventHook-0.0.1.dist-info/METADATA
pyEventHook-0.0.1.dist-info/WHEEL
pyEventHook-0.0.1.dist-info/top_level.txt
pyEventHook-0.0.1.dist-info/RECORD
