Metadata-Version: 2.1
Name: pyEventHook
Version: 0.0.1
Summary: A Python event implementation similar to the C# implementation
Home-page: https://github.com/ArielTriana/pyEventHook
Author: Ariel Alfonso Triana Pérez
Author-email: usich37@gmail.com
Classifier: Programming Language :: Python :: 3
Classifier: License :: OSI Approved :: MIT License
Classifier: Operating System :: OS Independent
Requires-Python: >=3.8
License-File: LICENSE
